Engr/__init__.py
Engr/util/__init__.py
Engr/util/correction_helper.py
Engr131_Winter_2022-0.0.7.dist-info/LICENSE
Engr131_Winter_2022-0.0.7.dist-info/METADATA
Engr131_Winter_2022-0.0.7.dist-info/WHEEL
Engr131_Winter_2022-0.0.7.dist-info/top_level.txt
Engr131_Winter_2022-0.0.7.dist-info/RECORD
